Metadata-Version: 1.0
Name: blobstore
Version: 0.1-alpha-1
Summary: Generic, zerorpc-powered, blobs storage
Home-page: http://github.com/rshk/blobstore
Author: Samuele Santi
Author-email: samuele@samuelesanti.com
License: GNU General Public License v3 or later (GPLv3+)
Platform: UNKNOWN
